ncurl/__init__.py
ncurl/app.py
ncurl/conf.py
ncurl/curl_utils.py
ncurl/utils.py
tests/__init__.py
tests/test_curl_utils.py
ncurl-0.7.6.dist-info/LICENSE
ncurl-0.7.6.dist-info/METADATA
ncurl-0.7.6.dist-info/WHEEL
ncurl-0.7.6.dist-info/entry_points.txt
ncurl-0.7.6.dist-info/top_level.txt
ncurl-0.7.6.dist-info/zip-safe
ncurl-0.7.6.dist-info/RECORD
