Metadata-Version: 2.1
Name: ncurl
Version: 0.7.6
Summary: Next generation of curl
Home-page: UNKNOWN
Author: bohan
Author-email: bohanzhang@foxmail.com
License: MIT License
Keywords: utils,curl
Platform: UNKNOWN
Requires-Dist: Pygments
Requires-Dist: requests
Requires-Dist: setuptools
Requires-Dist: colorama
